django_db_logs/__init__.py
django_db_logs/admin.py
django_db_logs/apps.py
django_db_logs/config.py
django_db_logs/db_log_handler.py
django_db_logs/models.py
django_db_logs/tests.py
django_db_logs/views.py
django_db_logs/migrations/0001_initial.py
django_db_logs/migrations/0002_auto_20190109_0052.py
django_db_logs/migrations/__init__.py
django_db_logs-0.1.dist-info/LICENSE
django_db_logs-0.1.dist-info/METADATA
django_db_logs-0.1.dist-info/WHEEL
django_db_logs-0.1.dist-info/top_level.txt
django_db_logs-0.1.dist-info/RECORD
